eisen_extras/__init__.py
eisen_extras-0.0.1.dist-info/LICENSE
eisen_extras-0.0.1.dist-info/METADATA
eisen_extras-0.0.1.dist-info/WHEEL
eisen_extras-0.0.1.dist-info/entry_points.txt
eisen_extras-0.0.1.dist-info/top_level.txt
eisen_extras-0.0.1.dist-info/RECORD
